{
  "routes": [
    {
      "route": {
        "id": 0,
        "weathers": [
          {
            "weather": {
              "route_percentage": 0.0,
              "precipitation": 100.0,
              "cloudiness": 0.0,
              "precipitation_deposits": 100.0,
              "wetness": 100.0,
              "wind_intensity": 100.0,
              "sun_azimuth_angle": -1.0,
              "sun_altitude_angle": 90.0,
              "fog_density": 2.0
            }
          },
          {
            "weather": {
              "route_percentage": 100.0,
              "precipitation": 100.0,
              "cloudiness": 0.0,
              "precipitation_deposits": 100.0,
              "wetness": 100.0,
              "wind_intensity": 100.0,
              "sun_azimuth_angle": -1.0,
              "sun_altitude_angle": 90.0,
              "fog_density": 2.0
            }
          }
        ],
        "waypoints": [
          {
            "position": {
              "x": -4.2223029136657715,
              "y": -150.22608947753906,
              "z": 0.0
            }
          },
          {
            "position": {
              "x": 72.98198935161064,
              "y": 16.422641650597434,
              "z": 0.0
            }
          }
        ],
        "scenarios": [
          {
            "scenario": {
              "name": "FollowLeadingVehicle_0",
              "type": "FollowLeadingVehicle",
              "trigger_point": {
                "x": 60.708831787109375,
                "y": 0.6798298358917236,
                "z": 0.0,
                "yaw": 6.628143310546875
              }
            }
          }
        ]
      }
    }
  ],
  "scenarios": [
    {
      "scenario": {
        "town": "Town07",
        "ego_vehicle": {
          "x": -4.2223029136657715,
          "y": -150.22608947753906,
          "z": 0,
          "yaw": 65.14286115887232,
          "model": "vehicle.toyota.prius",
          "name": "ego_vehicle"
        }
      }
    }
  ]
}