{
  "routes": [
    {
      "route": {
        "id": 39,
        "weathers": [
          {
            "weather": {
              "route_percentage": 0.0,
              "precipitation": 100.0,
              "cloudiness": 0.0,
              "precipitation_deposits": 100.0,
              "wetness": 100.0,
              "wind_intensity": 100.0,
              "sun_azimuth_angle": -1.0,
              "sun_altitude_angle": 90.0,
              "fog_density": 2.0
            }
          },
          {
            "weather": {
              "route_percentage": 100.0,
              "precipitation": 100.0,
              "cloudiness": 0.0,
              "precipitation_deposits": 100.0,
              "wetness": 100.0,
              "wind_intensity": 100.0,
              "sun_azimuth_angle": -1.0,
              "sun_altitude_angle": 90.0,
              "fog_density": 2.0
            }
          }
        ],
        "waypoints": [
          {
            "position": {
              "x": -145.40683300076276,
              "y": -101.20719430122273,
              "z": 0.0
            }
          },
          {
            "position": {
              "x": 218.04523474403996,
              "y": 200.6355771920273,
              "z": 0.0
            }
          }
        ],
        "scenarios": [
          {
            "scenario": {
              "name": "VehicleTurningRight_39",
              "type": "VehicleTurningRight",
              "trigger_point": {
                "x": -70.6647698402623,
                "y": -39.134768543750575,
                "z": 0.0,
                "yaw": 39.70924232401817
              }
            }
          }
        ]
      }
    }
  ],
  "scenarios": [
    {
      "scenario": {
        "town": "Town03",
        "ego_vehicle": {
          "x": -145.40683300076276,
          "y": -101.20719430122273,
          "z": 0,
          "yaw": 39.70924232401817,
          "model": "vehicle.toyota.prius",
          "name": "ego_vehicle"
        }
      }
    }
  ]
}