{
  "routes": [
    {
      "route": {
        "id": 41,
        "weathers": [
          {
            "weather": {
              "route_percentage": 0.0,
              "precipitation": 100.0,
              "cloudiness": 0.0,
              "precipitation_deposits": 100.0,
              "wetness": 100.0,
              "wind_intensity": 100.0,
              "sun_azimuth_angle": -1.0,
              "sun_altitude_angle": 90.0,
              "fog_density": 2.0
            }
          },
          {
            "weather": {
              "route_percentage": 100.0,
              "precipitation": 100.0,
              "cloudiness": 0.0,
              "precipitation_deposits": 100.0,
              "wetness": 100.0,
              "wind_intensity": 100.0,
              "sun_azimuth_angle": -1.0,
              "sun_altitude_angle": 90.0,
              "fog_density": 2.0
            }
          }
        ],
        "waypoints": [
          {
            "position": {
              "x": -10.352742143439501,
              "y": -35.9902175455823,
              "z": 0.0
            }
          },
          {
            "position": {
              "x": 33.41954994055923,
              "y": -7.123602497036162,
              "z": 0.0
            }
          }
        ],
        "scenarios": [
          {
            "scenario": {
              "name": "FollowLeadingVehicleWithObstacle_41",
              "type": "FollowLeadingVehicleWithObstacle",
              "trigger_point": {
                "x": 14.04921122969301,
                "y": -19.897804721893607,
                "z": 0.0,
                "yaw": 33.403746035963316
              }
            }
          }
        ]
      }
    }
  ],
  "scenarios": [
    {
      "scenario": {
        "town": "Town03",
        "ego_vehicle": {
          "x": -10.352742143439501,
          "y": -35.9902175455823,
          "z": 0,
          "yaw": 33.403746035963316,
          "model": "vehicle.toyota.prius",
          "name": "ego_vehicle"
        }
      }
    }
  ]
}