{
  "routes": [
    {
      "route": {
        "id": 0,
        "weathers": [
          {
            "weather": {
              "route_percentage": 0.0,
              "precipitation": 100.0,
              "cloudiness": 0.0,
              "precipitation_deposits": 100.0,
              "wetness": 100.0,
              "wind_intensity": 100.0,
              "sun_azimuth_angle": -1.0,
              "sun_altitude_angle": 90.0,
              "fog_density": 2.0
            }
          },
          {
            "weather": {
              "route_percentage": 100.0,
              "precipitation": 100.0,
              "cloudiness": 0.0,
              "precipitation_deposits": 100.0,
              "wetness": 100.0,
              "wind_intensity": 100.0,
              "sun_azimuth_angle": -1.0,
              "sun_altitude_angle": 90.0,
              "fog_density": 2.0
            }
          }
        ],
        "waypoints": [
          {
            "position": {
              "x": 59.81299591064453,
              "y": 24.850223541259766,
              "z": 0.0
            }
          },
          {
            "position": {
              "x": 28.78156042757476,
              "y": 68.29942591657147,
              "z": 0.0
            }
          }
        ],
        "scenarios": [
          {
            "scenario": {
              "name": "OppositeVehicleRunningRedLight_0",
              "type": "OppositeVehicleRunningRedLight",
              "trigger_point": {
                "x": -10.147546768188477,
                "y": 130.14862060546875,
                "z": 0.0,
                "yaw": -179.6478729248047
              }
            }
          }
        ]
      }
    }
  ],
  "scenarios": [
    {
      "scenario": {
        "town": "Town10HD",
        "ego_vehicle": {
          "x": 59.81299591064453,
          "y": 24.850223541259766,
          "z": 0,
          "yaw": 125.53443896435734,
          "model": "vehicle.toyota.prius",
          "name": "ego_vehicle"
        }
      }
    }
  ]
}